diskdantic/__init__.py
diskdantic/collection.py
diskdantic/exceptions.py
diskdantic/handlers.py
diskdantic/nested.py
diskdantic/utils.py
diskdantic-0.1.0.dist-info/METADATA
diskdantic-0.1.0.dist-info/WHEEL
diskdantic-0.1.0.dist-info/RECORD
