Metadata-Version: 2.4
Name: diskdantic
Version: 0.1.0
Summary: Disk-backed collections powered by Pydantic models.
Author-email: koaning <vincentwarmerdam@gmail.com>
Requires-Python: >=3.12
Requires-Dist: pydantic>=2.12.4
Requires-Dist: pyyaml>=6.0.3
